LICENSE
light_text_prepro/__init__.py
light_text_prepro/lprepro.py
light_text_prepro/rules/regex.yml
light_text_prepro-0.3.5.dist-info/LICENSE
light_text_prepro-0.3.5.dist-info/WHEEL
light_text_prepro-0.3.5.dist-info/METADATA
light_text_prepro-0.3.5.dist-info/RECORD
