Metadata-Version: 2.1
Name: light-text-prepro
Version: 0.3.5
Summary: Light Text Pre-processing permits to apply a chain of built-in regex rules to a input string.
Home-page: https://github.com/Arfius/light-text-prepro
License: MIT
Keywords: pre processing,regex,nlp
Author: Alfonso Farruggia
Requires-Python: >=3.6,<4.0
Classifier: License :: OSI Approved :: MIT License
Classifier: Programming Language :: Python :: 3
Classifier: Programming Language :: Python :: 3.10
Classifier: Programming Language :: Python :: 3.6
Classifier: Programming Language :: Python :: 3.7
Classifier: Programming Language :: Python :: 3.8
Classifier: Programming Language :: Python :: 3.9
Requires-Dist: PyYAML (>=5.4.1,<6.0.0)
Requires-Dist: flake8 (>=3.9.1,<4.0.0)
Project-URL: Bug Tracker, https://github.com/Arfius/light-text-prepro/issues
Project-URL: Repository, https://github.com/Arfius/light-text-prepro
